strif/__init__.py
strif/atomic_var.py
strif/py.typed
strif/strif.py
strif/string_replace.py
strif/string_template.py
strif-3.0.1.dist-info/METADATA
strif-3.0.1.dist-info/WHEEL
strif-3.0.1.dist-info/entry_points.txt
strif-3.0.1.dist-info/licenses/LICENSE
strif-3.0.1.dist-info/RECORD
