Metadata-Version: 2.4
Name: strif
Version: 3.0.1
Summary: Tiny, useful Python lib for strings and files
Project-URL: Repository, https://github.com/jlevy/strif
Author-email: Joshua Levy <joshua@cal.berkeley.edu>
License-Expression: MIT
License-File: LICENSE
Classifier: Development Status :: 4 - Beta
Classifier: Intended Audience :: Developers
Classifier: Operating System :: OS Independent
Classifier: Programming Language :: Python
Classifier: Programming Language :: Python :: 3
Classifier: Programming Language :: Python :: 3.11
Classifier: Programming Language :: Python :: 3.12
Classifier: Programming Language :: Python :: 3.13
Classifier: Typing :: Typed
Requires-Python: <4.0,>=3.10
